PaqueteProyecto/__init__.py
PaqueteProyecto/FuncionesPrueba/FuncionesMultivariables.py
PaqueteProyecto/FuncionesPrueba/FuncionesUnivariables.py
PaqueteProyecto/FuncionesPrueba/__init__.py
PaqueteProyecto/MetodosMultivariables/HookeJeeves.py
PaqueteProyecto/MetodosMultivariables/NelderMead.py
PaqueteProyecto/MetodosMultivariables/Reeves.py
PaqueteProyecto/MetodosMultivariables/__init__.py
PaqueteProyecto/MetodosMultivariables/cauchy.py
PaqueteProyecto/MetodosMultivariables/newton.py
PaqueteProyecto/MetodosMultivariables/randomwalked.py
PaqueteProyecto/MetodosUnivariables/BusquedaDorada.py
PaqueteProyecto/MetodosUnivariables/Fibonacci.py
PaqueteProyecto/MetodosUnivariables/IntervalHalving.py
PaqueteProyecto/MetodosUnivariables/NewtonRaph.py
PaqueteProyecto/MetodosUnivariables/Secante.py
PaqueteProyecto/MetodosUnivariables/__init__.py
PaqueteProyecto/MetodosUnivariables/biseccion.py
PaqueteProyecto-0.2.dist-info/METADATA
PaqueteProyecto-0.2.dist-info/WHEEL
PaqueteProyecto-0.2.dist-info/top_level.txt
PaqueteProyecto-0.2.dist-info/RECORD
